pytest_cookies/__init__.py
pytest_cookies/plugin.py
pytest_cookies-0.7.0.dist-info/LICENSE
pytest_cookies-0.7.0.dist-info/METADATA
pytest_cookies-0.7.0.dist-info/WHEEL
pytest_cookies-0.7.0.dist-info/entry_points.txt
pytest_cookies-0.7.0.dist-info/top_level.txt
pytest_cookies-0.7.0.dist-info/RECORD
