Metadata-Version: 2.1
Name: pytest-cookies
Version: 0.7.0
Summary: The pytest plugin for your Cookiecutter templates. 🍪
Home-page: https://github.com/hackebrot/pytest-cookies
Author: Raphael Pierzina
Author-email: raphael@hackebrot.de
Maintainer: Raphael Pierzina
Maintainer-email: raphael@hackebrot.de
License: MIT
Project-URL: Repository, https://github.com/hackebrot/pytest-cookies
Project-URL: Issues, https://github.com/hackebrot/pytest-cookies/issues
Keywords: cookiecutter,pytest
Classifier: Development Status :: 5 - Production/Stable
Classifier: Intended Audience :: Developers
Classifier: License :: OSI Approved :: MIT License
Classifier: Operating System :: OS Independent
Classifier: Programming Language :: Python :: 3 :: Only
Classifier: Programming Language :: Python :: 3.7
Classifier: Programming Language :: Python :: 3.8
Classifier: Programming Language :: Python :: 3.9
Classifier: Programming Language :: Python :: 3.10
Classifier: Programming Language :: Python :: 3.11
Classifier: Programming Language :: Python :: Implementation :: CPython
Classifier: Programming Language :: Python
Classifier: Topic :: Software Development :: Testing
Classifier: Framework :: Pytest
Requires-Python: >=3.7
License-File: LICENSE
Requires-Dist: cookiecutter (>=2.1.0)
Requires-Dist: pytest (>=3.9.0)
